illallangi/django/mastodon/__init__.py
illallangi/django/mastodon/__version__.py
illallangi/django/mastodon/apps.py
illallangi/django/mastodon/adapters/__init__.py
illallangi/django/mastodon/adapters/mastodon.py
illallangi/django/mastodon/admin/__init__.py
illallangi/django/mastodon/admin/status.py
illallangi/django/mastodon/diffsyncmodels/__init__.py
illallangi/django/mastodon/diffsyncmodels/status.py
illallangi/django/mastodon/management/__init__.py
illallangi/django/mastodon/management/commands/__init__.py
illallangi/django/mastodon/management/commands/syncmastodon.py
illallangi/django/mastodon/migrations/0001_initial.py
illallangi/django/mastodon/migrations/__init__.py
illallangi/django/mastodon/models/__init__.py
illallangi/django/mastodon/models/status.py
illallangi/django/mastodon/static/mastodon/statuses.png
illallangi/django/mastodon/templates/mastodon/home.html
illallangi/django/mastodon/templates/mastodon/status.html
illallangi/django/mastodon/templates/mastodon/statuses.html
illallangi/django/mastodon/urls/__init__.py
illallangi/django/mastodon/urls/status.py
illallangi/django/mastodon/views/__init__.py
illallangi/django/mastodon/views/favicon.py
illallangi/django/mastodon/views/home/__init__.py
illallangi/django/mastodon/views/home/home_html.py
illallangi/django/mastodon/views/status/__init__.py
illallangi/django/mastodon/views/status/status_html.py
illallangi/django/mastodon/views/status/statuses_html.py
illallangi_django_mastodon-0.1.1.dist-info/METADATA
illallangi_django_mastodon-0.1.1.dist-info/WHEEL
illallangi_django_mastodon-0.1.1.dist-info/licenses/LICENSE
illallangi_django_mastodon-0.1.1.dist-info/RECORD
